{"dipole": [-0.49633951, 0.30264126, 0.00605089], "partial charges": [-0.15901582, 0.05590433, -0.09680697, 0.06602293, 0.06375329, 0.07014224], "mulliken charges": [-0.11012, 0.08878, -0.10117, 0.0341, 0.04453, 0.04388], "cm5 charges": [-0.11497, 0.03221, -0.20152, 0.0902, 0.097, 0.09709], "FUKUI+": [-0.255, -0.117, -0.129, -0.168, -0.17, -0.162], "FUKUI-": [-0.482, -0.038, -0.1, -0.126, -0.137, -0.118], "FUKUIrad": [-0.368, -0.077, -0.114, -0.147, -0.153, -0.14], "s proportion": [1.941, 1.061, 1.047, 0.966, 0.955, 0.956], "p proportion": [5.18, 2.85, 3.054, 0.0, 0.0, 0.0], "d proportion": [-0.01, 0.0, 0.0, 0.0, 0.0, 0.0], "Coordination numbers": [0.937, 2.797, 2.876, 0.925, 0.925, 0.925], "Dispersion coefficient C6": [104.126, 26.732, 30.432, 2.13, 2.155, 2.084], "Polarizability alpha": [15.611, 8.47, 9.043, 2.282, 2.296, 2.257], "FOD": [0.0, 0.0, 0.0, 0.0, 0.0, 0.0], "FOD s proportion": [0.0, 0.0, 0.0, 0.0, 0.0, 0.0], "FOD p proportion": [0.0, 0.0, 0.0, 0.0, 0.0, 0.0], "FOD d proportion": [0.0, 0.0, 0.0, 0.0, 0.0, 0.0], "total energy": -10.321469, "HOMO-LUMO gap/eV": 4.64919732, "electronic energy": -10.42904398, "Dipole module/D": 1.478, "Total charge": 0.0, "HOMO": -11.0527, "LUMO": -6.4035, "Fermi-level/eV": -8.7281, "Total dispersion C6": 637.763892, "Total dispersion C8": 19193.768425, "Total polarizability alpha": 39.959765, "Total FOD": 0.0}